{
  "setting": {},
  "condition": {
    "plugin": {
      "list": []
    },
    "game": {
      "list": []
    },
    "gamePlugin": {
      "list": []
    },
    "miniprogram": {
      "list": [
        {
          "name": "pages/service-detail/service-detail",
          "pathName": "pages/service-detail/service-detail",
          "query": "service_id=464",
          "scene": null
        },
        {
          "name": "登录",
          "pathName": "pages/login/login",
          "query": "",
          "scene": null
        }
      ]
    }
  }
}